minder/research_portal_client/__init__.py
minder/research_portal_client/_api_client.py
minder/research_portal_client/_configuration.py
minder/research_portal_client/_job_manager.py
minder/research_portal_client/_serializer.py
minder/research_portal_client/py.typed
minder/research_portal_client/_utils/__init__.py
minder/research_portal_client/_utils/_rest_object.py
minder/research_portal_client/api/__init__.py
minder/research_portal_client/api/_download_api.py
minder/research_portal_client/api/_export_api.py
minder/research_portal_client/api/_info_api.py
minder/research_portal_client/api/_reports_api.py
minder/research_portal_client/models/__init__.py
minder/research_portal_client/models/_available_datasets_response.py
minder/research_portal_client/models/_export_job_request.py
minder/research_portal_client/models/_export_job_response.py
minder/research_portal_client/models/_organizations_response.py
minder_research_portal_client-0.1.10.dist-info/METADATA
minder_research_portal_client-0.1.10.dist-info/WHEEL
minder_research_portal_client-0.1.10.dist-info/top_level.txt
minder_research_portal_client-0.1.10.dist-info/RECORD
