Metadata-Version: 2.4
Name: minder.research_portal_client
Version: 0.1.10
Author: UK DRI Care Research & Technology centre
Requires-Python: >=3.8
Requires-Dist: aiohttp[speedups]>=3.8.1
Requires-Dist: backoff>=1.11.1
Requires-Dist: python-dateutil>=2.8.2
